Metadata-Version: 2.1
Name: fastcode
Version: 1.0.0
Summary: A Python Library for simplifying the use of repetitive code in my python projects.
Home-page: https://github.com/TareqAbeda/Python_Library
Author: Tareq Abeda
Author-email: TareqAbeda@outlook.com
License: MIT
Keywords: Protocols
Classifier: Development Status :: 1 - Planning
Classifier: Intended Audience :: Developers
Classifier: License :: OSI Approved :: MIT License
Classifier: Operating System :: Microsoft :: Windows :: Windows 11
Classifier: Programming Language :: Python :: 3.12
